monfig/__init__.py
monfig/_monfig.py
monfig-0.1.0.dist-info/LICENSE
monfig-0.1.0.dist-info/METADATA
monfig-0.1.0.dist-info/WHEEL
monfig-0.1.0.dist-info/top_level.txt
monfig-0.1.0.dist-info/RECORD
