Metadata-Version: 2.1
Name: monfig
Version: 0.1.0
Summary: An interesting library to help use python module as configuration and do check like pylance.
Home-page: https://github.com/universetraveller/monfig-python
Author: universetraveller
Author-email: universetraveller@outlook.com
License: MIT
Platform: UNKNOWN
Classifier: License :: OSI Approved :: MIT License
Classifier: Programming Language :: Python
Classifier: Programming Language :: Python :: 3
Classifier: Programming Language :: Python :: Implementation :: CPython
Classifier: Topic :: Software Development
Classifier: Topic :: Software Development :: Libraries :: Python Modules
Requires-Python: >=3.8.0
